SRT2LRC/Converter.py
SRT2LRC/__init__.py
SRT2LRC-1.0.dist-info/LICENSE
SRT2LRC-1.0.dist-info/METADATA
SRT2LRC-1.0.dist-info/WHEEL
SRT2LRC-1.0.dist-info/top_level.txt
SRT2LRC-1.0.dist-info/RECORD
