Metadata-Version: 2.1
Name: SRT2LRC
Version: 1.0
Summary: Converts from SRT to LRC and vice versa.
Home-page: https://github.com/Oni-Sparrow/SRT2LRC
Author: Oni-Sparrow
Author-email: omarashrafgeddawy@gmail.com
Classifier: Programming Language :: Python :: 3
Classifier: License :: OSI Approved :: MIT License
Classifier: Operating System :: OS Independent
Requires-Python: >=3.6
License-File: LICENSE
